wheatley/__init__.py
wheatley/__main__.py
wheatley/aliases.py
wheatley/bell.py
wheatley/bot.py
wheatley/calls.py
wheatley/main.py
wheatley/page_parser.py
wheatley/parsing.py
wheatley/stroke.py
wheatley/tower.py
wheatley/version.txt
wheatley/rhythm/__init__.py
wheatley/rhythm/abstract_rhythm.py
wheatley/rhythm/regression.py
wheatley/rhythm/wait_for_user.py
wheatley/row_generation/__init__.py
wheatley/row_generation/complib_composition_generator.py
wheatley/row_generation/dixonoids_generator.py
wheatley/row_generation/helpers.py
wheatley/row_generation/method_place_notation_generator.py
wheatley/row_generation/place_holder_generator.py
wheatley/row_generation/place_notation_generator.py
wheatley/row_generation/plain_hunt_generator.py
wheatley/row_generation/row_generator.py
wheatley-0.8.0.dist-info/LICENSE
wheatley-0.8.0.dist-info/METADATA
wheatley-0.8.0.dist-info/WHEEL
wheatley-0.8.0.dist-info/entry_points.txt
wheatley-0.8.0.dist-info/top_level.txt
wheatley-0.8.0.dist-info/RECORD
