Metadata-Version: 2.1
Name: wheatley
Version: 0.8.0
Summary: A program that will ring any set of bells in Ringing Room.
Home-page: https://github.com/Kneasle/wheatley/
Author: Ben White-Horne
Author-email: kneasle@gmail.com
License: MIT
Platform: any
Classifier: Programming Language :: Python :: 3
Classifier: License :: OSI Approved :: MIT License
Classifier: Operating System :: OS Independent
Requires-Python: >=3.6
License-File: LICENSE
Requires-Dist: python-engineio (~=4.5.1)
Requires-Dist: python-socketio (~=5.8.0)
Requires-Dist: requests
Requires-Dist: websocket-client
Requires-Dist: numpy (==1.19.5) ; python_version < "3.8"
Requires-Dist: numpy ; python_version >= "3.8"
